biglup_cometa-1.2.1.post6.dist-info/licenses/LICENSE
cometa/__init__.py
cometa/_aiken_cffi.py
cometa/_aiken_ffi.py
cometa/_cardano_cffi.py
cometa/_ffi.py
cometa/_ffi_build.py
cometa/buffer.py
cometa/cardano.py
cometa/errors.py
cometa/time.py
cometa/_cdef/aiken-c.cdef
cometa/_cdef/cardano-c.cdef
cometa/_native/linux-armv6/libaiken_c.so
cometa/_native/linux-armv6/libcardano-c.so
cometa/address/__init__.py
cometa/address/address.py
cometa/address/address_type.py
cometa/address/base_address.py
cometa/address/byron_address.py
cometa/address/byron_address_attributes.py
cometa/address/byron_address_type.py
cometa/address/enterprise_address.py
cometa/address/pointer_address.py
cometa/address/reward_address.py
cometa/address/stake_pointer.py
cometa/aiken/__init__.py
cometa/aiken/aiken_tx_evaluator.py
cometa/aiken/script_util.py
cometa/assets/__init__.py
cometa/assets/asset_id.py
cometa/assets/asset_id_list.py
cometa/assets/asset_id_map.py
cometa/assets/asset_name.py
cometa/assets/asset_name_list.py
cometa/assets/asset_name_map.py
cometa/assets/multi_asset.py
cometa/assets/policy_id_list.py
cometa/auxiliary_data/__init__.py
cometa/auxiliary_data/auxiliary_data.py
cometa/auxiliary_data/metadatum.py
cometa/auxiliary_data/metadatum_kind.py
cometa/auxiliary_data/metadatum_label_list.py
cometa/auxiliary_data/metadatum_list.py
cometa/auxiliary_data/metadatum_map.py
cometa/auxiliary_data/plutus_v1_script_list.py
cometa/auxiliary_data/plutus_v2_script_list.py
cometa/auxiliary_data/plutus_v3_script_list.py
cometa/auxiliary_data/transaction_metadata.py
cometa/bip39/__init__.py
cometa/bip39/bip39.py
cometa/cbor/__init__.py
cometa/cbor/cbor_major_type.py
cometa/cbor/cbor_reader.py
cometa/cbor/cbor_reader_state.py
cometa/cbor/cbor_simple_value.py
cometa/cbor/cbor_tag.py
cometa/cbor/cbor_writer.py
cometa/certificates/__init__.py
cometa/certificates/auth_committee_hot_cert.py
cometa/certificates/certificate.py
cometa/certificates/certificate_set.py
cometa/certificates/certificate_type.py
cometa/certificates/genesis_key_delegation_cert.py
biglup_cometa-1.2.1.post6.dist-info/METADATA
biglup_cometa-1.2.1.post6.dist-info/WHEEL
biglup_cometa-1.2.1.post6.dist-info/top_level.txt
biglup_cometa-1.2.1.post6.dist-info/RECORD
