Metadata-Version: 2.4
Name: biglup-cometa
Version: 1.2.1.post6
Summary: Python bindings for libcardano-c (Cometa project)
Author-email: Angel Castillo <angel.castillob@prototnmail.io>
License:                                  Apache License
Project-URL: Homepage, https://cometa.dev
Project-URL: Source, https://github.com/Biglup/cometa.py
Project-URL: Issues, https://github.com/Biglup/cometa.py/issues
Classifier: Programming Language :: Python :: 3
Classifier: License :: OSI Approved :: Apache Software License
Classifier: Operating System :: OS Independent
Requires-Python: >=3.9
License-File: LICENSE
Requires-Dist: cffi>=1.16.0
Dynamic: license-file
